your_e2b_clone.py
bettere2b-1.0.0.dist-info/METADATA
bettere2b-1.0.0.dist-info/WHEEL
bettere2b-1.0.0.dist-info/entry_points.txt
bettere2b-1.0.0.dist-info/top_level.txt
bettere2b-1.0.0.dist-info/RECORD
