Metadata-Version: 2.4
Name: bettere2b
Version: 1.0.0
Summary: BetterE2B - Drop-in replacement for e2b-code-interpreter with dynamic subdomain support
Home-page: https://github.com/playauraai/bettere2b
Author: Your Name
Author-email: Your Name <your.email@example.com>
Maintainer-email: Your Name <your.email@example.com>
License: MIT
Project-URL: Homepage, https://github.com/playauraai/bettere2b
Project-URL: Documentation, https://github.com/playauraai/bettere2b#readme
Project-URL: Repository, https://github.com/playauraai/bettere2b
Project-URL: Bug Tracker, https://github.com/playauraai/bettere2b/issues
Keywords: e2b,sandbox,code-execution,docker,subdomain,dynamic,sdk,api,python
Classifier: Development Status :: 5 - Production/Stable
Classifier: Intended Audience :: Developers
Classifier: License :: OSI Approved :: MIT License
Classifier: Operating System :: OS Independent
Classifier: Programming Language :: Python :: 3
Classifier: Programming Language :: Python :: 3.8
Classifier: Programming Language :: Python :: 3.9
Classifier: Programming Language :: Python :: 3.10
Classifier: Programming Language :: Python :: 3.11
Classifier: Programming Language :: Python :: 3.12
Classifier: Topic :: Software Development :: Libraries :: Python Modules
Classifier: Topic :: Software Development :: Testing
Classifier: Topic :: System :: Distributed Computing
Requires-Python: >=3.8
Requires-Dist: requests>=2.25.0
Provides-Extra: dev
Requires-Dist: pytest>=6.0; extra == "dev"
Requires-Dist: pytest-asyncio>=0.18.0; extra == "dev"
Requires-Dist: black>=21.0; extra == "dev"
Requires-Dist: flake8>=3.9; extra == "dev"
Requires-Dist: mypy>=0.910; extra == "dev"
Provides-Extra: test
Requires-Dist: pytest>=6.0; extra == "test"
Requires-Dist: pytest-asyncio>=0.18.0; extra == "test"
Dynamic: author
Dynamic: home-page
Dynamic: requires-python
